{
  "01-01": { "name": "National Bloody Mary Day", "wikipedia": "Bloody_Mary_(cocktail)", "link": "https://nationaltoday.com/national-bloody-mary-day/" },
  "01-02": { "name": "National Science Fiction Day", "wikipedia": "Science_fiction", "link": "https://nationaltoday.com/national-science-fiction-day/" },
  "01-03": { "name": "National Chocolate Covered Cherry Day", "wikipedia": "Chocolate-covered_cherry", "link": "https://nationaltoday.com/national-chocolate-covered-cherry-day/" },
  "01-04": { "name": "National Spaghetti Day", "wikipedia": "Spaghetti", "link": "https://nationaltoday.com/national-spaghetti-day/" },
  "01-05": { "name": "National Bird Day", "wikipedia": "Bird", "link": "https://nationaltoday.com/national-bird-day/" },
  "01-06": { "name": "National Shortbread Day", "wikipedia": "Shortbread", "link": "https://nationaltoday.com/national-shortbread-day/" },
  "01-07": { "name": "National Tempura Day", "wikipedia": "Tempura", "link": "https://nationaltoday.com/national-tempura-day/" },
  "01-08": { "name": "National English Toffee Day", "wikipedia": "Toffee", "link": "https://nationaltoday.com/national-english-toffee-day/" },
  "01-09": { "name": "National Apricot Day", "wikipedia": "Apricot", "link": "https://nationaltoday.com/national-apricot-day/" },
  "01-10": { "name": "National Bittersweet Chocolate Day", "wikipedia": "Chocolate", "link": "https://nationaltoday.com/national-bittersweet-chocolate-day/" },
  "01-11": { "name": "National Milk Day", "wikipedia": "Milk", "link": "https://nationaltoday.com/national-milk-day/" },
  "01-12": { "name": "National Marzipan Day", "wikipedia": "Marzipan", "link": "https://nationaltoday.com/national-marzipan-day/" },
  "01-13": { "name": "National Rubber Ducky Day", "wikipedia": "Rubber_duck", "link": "https://nationaltoday.com/national-rubber-ducky-day/" },
  "01-14": { "name": "National Dress Up Your Pet Day", "wikipedia": "Pet_clothing", "link": "https://nationaltoday.com/national-dress-up-your-pet-day/" },
  "01-15": { "name": "National Hat Day", "wikipedia": "Hat", "link": "https://nationaltoday.com/national-hat-day/" },
  "01-16": { "name": "National Fig Newton Day", "wikipedia": "Fig_Newton", "link": "https://nationaltoday.com/national-fig-newton-day/" },
  "01-17": { "name": "National Hot Buttered Rum Day", "wikipedia": "Hot_buttered_rum", "link": "https://nationaltoday.com/national-hot-buttered-rum-day/" },
  "01-18": { "name": "National Winnie the Pooh Day", "wikipedia": "Winnie-the-Pooh", "link": "https://nationaltoday.com/national-winnie-the-pooh-day/" },
  "01-19": { "name": "National Popcorn Day", "wikipedia": "Popcorn", "link": "https://nationaltoday.com/national-popcorn-day/" },
  "01-20": { "name": "National Cheese Lover's Day", "wikipedia": "Cheese", "link": "https://nationaltoday.com/national-cheese-lovers-day/" },
  "01-21": { "name": "National Squirrel Appreciation Day", "wikipedia": "Squirrel", "link": "https://nationaltoday.com/national-squirrel-appreciation-day/" },
  "01-22": { "name": "National Blonde Brownie Day", "wikipedia": "Blondie_(baked_goods)", "link": "https://nationaltoday.com/national-blonde-brownie-day/" },
  "01-23": { "name": "National Pie Day", "wikipedia": "Pie", "link": "https://nationaltoday.com/national-pie-day/" },
  "01-24": { "name": "National Peanut Butter Day", "wikipedia": "Peanut_butter", "link": "https://nationaltoday.com/national-peanut-butter-day/" },
  "01-25": { "name": "National Irish Coffee Day", "wikipedia": "Irish_coffee", "link": "https://nationaltoday.com/national-irish-coffee-day/" },
  "01-26": { "name": "National Pistachio Day", "wikipedia": "Pistachio", "link": "https://nationaltoday.com/national-pistachio-day/" },
  "01-27": { "name": "National Chocolate Cake Day", "wikipedia": "Chocolate_cake", "link": "https://nationaltoday.com/national-chocolate-cake-day/" },
  "01-28": { "name": "National Kazoo Day", "wikipedia": "Kazoo", "link": "https://nationaltoday.com/national-kazoo-day/" },
  "01-29": { "name": "National Corn Chip Day", "wikipedia": "Corn_chip", "link": "https://nationaltoday.com/national-corn-chip-day/" },
  "01-30": { "name": "National Croissant Day", "wikipedia": "Croissant", "link": "https://nationaltoday.com/national-croissant-day/" },
  "01-31": { "name": "National Hot Chocolate Day", "wikipedia": "Hot_chocolate", "link": "https://nationaltoday.com/national-hot-chocolate-day/" },

  "02-01": { "name": "National Baked Alaska Day", "wikipedia": "Baked_Alaska", "link": "https://nationaltoday.com/national-baked-alaska-day/" },
  "02-02": { "name": "Groundhog Day", "wikipedia": "Groundhog_Day", "link": "https://nationaltoday.com/groundhog-day/" },
  "02-03": { "name": "National Carrot Cake Day", "wikipedia": "Carrot_cake", "link": "https://nationaltoday.com/national-carrot-cake-day/" },
  "02-04": { "name": "National Homemade Soup Day", "wikipedia": "Soup", "link": "https://nationaltoday.com/national-homemade-soup-day/" },
  "02-05": { "name": "National Weatherperson's Day", "wikipedia": "Weather_forecasting", "link": "https://nationaltoday.com/national-weatherpersons-day/" },
  "02-06": { "name": "National Chopsticks Day", "wikipedia": "Chopsticks", "link": "https://nationaltoday.com/national-chopsticks-day/" },
  "02-07": { "name": "National Fettuccine Alfredo Day", "wikipedia": "Fettuccine_Alfredo", "link": "https://nationaltoday.com/national-fettuccine-alfredo-day/" },
  "02-08": { "name": "National Kite Flying Day", "wikipedia": "Kite", "link": "https://nationaltoday.com/national-kite-flying-day/" },
  "02-09": { "name": "National Pizza Day", "wikipedia": "Pizza", "link": "https://nationaltoday.com/national-pizza-day/" },
  "02-10": { "name": "National Umbrella Day", "wikipedia": "Umbrella", "link": "https://nationaltoday.com/national-umbrella-day/" },
  "02-11": { "name": "National Peppermint Patty Day", "wikipedia": "Peppermint_Pattie", "link": "https://nationaltoday.com/national-peppermint-patty-day/" },
  "02-12": { "name": "National Plum Pudding Day", "wikipedia": "Christmas_pudding", "link": "https://nationaltoday.com/national-plum-pudding-day/" },
  "02-13": { "name": "National Italian Food Day", "wikipedia": "Italian_cuisine", "link": "https://nationaltoday.com/national-italian-food-day/" },
  "02-14": { "name": "National Ferris Wheel Day", "wikipedia": "Ferris_wheel", "link": "https://nationaltoday.com/national-ferris-wheel-day/" },
  "02-15": { "name": "National Gumdrop Day", "wikipedia": "Gumdrop", "link": "https://nationaltoday.com/national-gumdrop-day/" },
  "02-16": { "name": "National Almond Day", "wikipedia": "Almond", "link": "https://nationaltoday.com/national-almond-day/" },
  "02-17": { "name": "National Random Acts of Kindness Day", "wikipedia": "Random_act_of_kindness", "link": "https://nationaltoday.com/national-random-acts-of-kindness-day/" },
  "02-18": { "name": "National Drink Wine Day", "wikipedia": "Wine", "link": "https://nationaltoday.com/national-drink-wine-day/" },
  "02-19": { "name": "National Chocolate Mint Day", "wikipedia": "Chocolate_mint", "link": "https://nationaltoday.com/national-chocolate-mint-day/" },
  "02-20": { "name": "National Muffin Day", "wikipedia": "Muffin", "link": "https://nationaltoday.com/national-muffin-day/" },
  "02-21": { "name": "National Sticky Bun Day", "wikipedia": "Sticky_bun", "link": "https://nationaltoday.com/national-sticky-bun-day/" },
  "02-22": { "name": "National Margarita Day", "wikipedia": "Margarita", "link": "https://nationaltoday.com/national-margarita-day/" },
  "02-23": { "name": "National Banana Bread Day", "wikipedia": "Banana_bread", "link": "https://nationaltoday.com/national-banana-bread-day/" },
  "02-24": { "name": "National Tortilla Chip Day", "wikipedia": "Tortilla_chip", "link": "https://nationaltoday.com/national-tortilla-chip-day/" },
  "02-25": { "name": "National Clam Chowder Day", "wikipedia": "Clam_chowder", "link": "https://nationaltoday.com/national-clam-chowder-day/" },
  "02-26": { "name": "National Pistachio Day", "wikipedia": "Pistachio", "link": "https://nationaltoday.com/national-pistachio-day/" },
  "02-27": { "name": "National Polar Bear Day", "wikipedia": "Polar_bear", "link": "https://nationaltoday.com/national-polar-bear-day/" },
  "02-28": { "name": "National Public Sleeping Day", "wikipedia": "Sleep", "link": "https://nationaltoday.com/national-public-sleeping-day/" },
  "02-29": { "name": "National Leap Day", "wikipedia": "Leap_year", "link": "https://nationaltoday.com/national-leap-day/" },

  "03-01": { "name": "National Peanut Butter Lover's Day", "wikipedia": "Peanut_butter", "link": "https://nationaltoday.com/national-peanut-butter-lovers-day/" },
  "03-02": { "name": "National Dr. Seuss Day", "wikipedia": "Dr._Seuss", "link": "https://nationaltoday.com/national-read-across-america-day/" },
  "03-03": { "name": "National Mulled Wine Day", "wikipedia": "Mulled_wine", "link": "https://nationaltoday.com/national-mulled-wine-day/" },
  "03-04": { "name": "National Grammar Day", "wikipedia": "Grammar", "link": "https://nationaltoday.com/national-grammar-day/" },
  "03-05": { "name": "National Absinthe Day", "wikipedia": "Absinthe", "link": "https://nationaltoday.com/national-absinthe-day/" },
  "03-06": { "name": "National Oreo Cookie Day", "wikipedia": "Oreo", "link": "https://nationaltoday.com/national-oreo-cookie-day/" },
  "03-07": { "name": "National Cereal Day", "wikipedia": "Breakfast_cereal", "link": "https://nationaltoday.com/national-cereal-day/" },
  "03-08": { "name": "National Peanut Cluster Day", "wikipedia": "Peanut", "link": "https://nationaltoday.com/national-peanut-cluster-day/" },
  "03-09": { "name": "National Meatball Day", "wikipedia": "Meatball", "link": "https://nationaltoday.com/national-meatball-day/" },
  "03-10": { "name": "National Mario Day", "wikipedia": "Mario_(franchise)", "link": "https://nationaltoday.com/national-mario-day/" },
  "03-11": { "name": "National Oatmeal Cookie Day", "wikipedia": "Oatmeal_cookie", "link": "https://nationaltoday.com/national-oatmeal-cookie-day/" },
  "03-12": { "name": "National Baked Scallops Day", "wikipedia": "Scallop", "link": "https://nationaltoday.com/national-baked-scallops-day/" },
  "03-13": { "name": "National Coconut Torte Day", "wikipedia": "Coconut", "link": "https://nationaltoday.com/national-coconut-torte-day/" },
  "03-14": { "name": "National Pi Day", "wikipedia": "Pi", "link": "https://nationaltoday.com/national-pi-day/" },
  "03-15": { "name": "National Pears Helene Day", "wikipedia": "Pear", "link": "https://nationaltoday.com/national-pears-helene-day/" },
  "03-16": { "name": "National Artichoke Hearts Day", "wikipedia": "Artichoke", "link": "https://nationaltoday.com/national-artichoke-hearts-day/" },
  "03-17": { "name": "National Corned Beef and Cabbage Day", "wikipedia": "Corned_beef", "link": "https://nationaltoday.com/national-corned-beef-and-cabbage-day/" },
  "03-18": { "name": "National Lacy Oatmeal Cookie Day", "wikipedia": "Cookie", "link": "https://nationaltoday.com/national-lacy-oatmeal-cookie-day/" },
  "03-19": { "name": "National Poultry Day", "wikipedia": "Chicken_as_food", "link": "https://nationaltoday.com/national-poultry-day/" },
  "03-20": { "name": "National Ravioli Day", "wikipedia": "Ravioli", "link": "https://nationaltoday.com/national-ravioli-day/" },
  "03-21": { "name": "National French Bread Day", "wikipedia": "Baguette", "link": "https://nationaltoday.com/national-french-bread-day/" },
  "03-22": { "name": "National Water Day", "wikipedia": "Water", "link": "https://nationaltoday.com/world-water-day/" },
  "03-23": { "name": "National Puppy Day", "wikipedia": "Puppy", "link": "https://nationaltoday.com/national-puppy-day/" },
  "03-24": { "name": "National Chocolate Covered Raisins Day", "wikipedia": "Raisin", "link": "https://nationaltoday.com/national-chocolate-covered-raisins-day/" },
  "03-25": { "name": "National Lobster Newburg Day", "wikipedia": "Lobster_Newburg", "link": "https://nationaltoday.com/national-lobster-newburg-day/" },
  "03-26": { "name": "National Spinach Day", "wikipedia": "Spinach", "link": "https://nationaltoday.com/national-spinach-day/" },
  "03-27": { "name": "National Spanish Paella Day", "wikipedia": "Paella", "link": "https://nationaltoday.com/national-spanish-paella-day/" },
  "03-28": { "name": "National Black Forest Cake Day", "wikipedia": "Black_Forest_cake", "link": "https://nationaltoday.com/national-black-forest-cake-day/" },
  "03-29": { "name": "National Lemon Chiffon Cake Day", "wikipedia": "Chiffon_cake", "link": "https://nationaltoday.com/national-lemon-chiffon-cake-day/" },
  "03-30": { "name": "National Virtual Vacation Day", "wikipedia": "Virtual_tourism", "link": "https://nationaltoday.com/national-virtual-vacation-day/" },
  "03-31": { "name": "National Crayon Day", "wikipedia": "Crayon", "link": "https://nationaltoday.com/national-crayon-day/" },

  "04-01": { "name": "April Fools' Day", "wikipedia": "April_Fools%27_Day", "link": "https://nationaltoday.com/april-fools-day/" },
  "04-02": { "name": "National Peanut Butter and Jelly Day", "wikipedia": "Peanut_butter_and_jelly_sandwich", "link": "https://nationaltoday.com/national-peanut-butter-and-jelly-day/" },
  "04-03": { "name": "National Chocolate Mousse Day", "wikipedia": "Chocolate_mousse", "link": "https://nationaltoday.com/national-chocolate-mousse-day/" },
  "04-04": { "name": "National Cordon Bleu Day", "wikipedia": "Chicken_cordon_bleu", "link": "https://nationaltoday.com/national-cordon-bleu-day/" },
  "04-05": { "name": "National Deep Dish Pizza Day", "wikipedia": "Chicago-style_pizza", "link": "https://nationaltoday.com/national-deep-dish-pizza-day/" },
  "04-06": { "name": "National Caramel Popcorn Day", "wikipedia": "Caramel_corn", "link": "https://nationaltoday.com/national-caramel-popcorn-day/" },
  "04-07": { "name": "National Beer Day", "wikipedia": "Beer", "link": "https://nationaltoday.com/national-beer-day/" },
  "04-08": { "name": "National Zoo Lovers Day", "wikipedia": "Zoo", "link": "https://nationaltoday.com/national-zoo-lovers-day/" },
  "04-09": { "name": "National Unicorn Day", "wikipedia": "Unicorn", "link": "https://nationaltoday.com/national-unicorn-day/" },
  "04-10": { "name": "National Siblings Day", "wikipedia": "Sibling", "link": "https://nationaltoday.com/national-siblings-day/" },
  "04-11": { "name": "National Cheese Fondue Day", "wikipedia": "Fondue", "link": "https://nationaltoday.com/national-cheese-fondue-day/" },
  "04-12": { "name": "National Grilled Cheese Day", "wikipedia": "Cheese_sandwich", "link": "https://nationaltoday.com/national-grilled-cheese-day/" },
  "04-13": { "name": "National Scrabble Day", "wikipedia": "Scrabble", "link": "https://nationaltoday.com/national-scrabble-day/" },
  "04-14": { "name": "National Gardening Day", "wikipedia": "Gardening", "link": "https://nationaltoday.com/national-gardening-day/" },
  "04-15": { "name": "National Glazed Spiral Ham Day", "wikipedia": "Ham", "link": "https://nationaltoday.com/national-glazed-spiral-ham-day/" },
  "04-16": { "name": "National Eggs Benedict Day", "wikipedia": "Eggs_Benedict", "link": "https://nationaltoday.com/national-eggs-benedict-day/" },
  "04-17": { "name": "National Cheeseball Day", "wikipedia": "Cheese_ball", "link": "https://nationaltoday.com/national-cheeseball-day/" },
  "04-18": { "name": "National Animal Crackers Day", "wikipedia": "Animal_cracker", "link": "https://nationaltoday.com/national-animal-crackers-day/" },
  "04-19": { "name": "National Garlic Day", "wikipedia": "Garlic", "link": "https://nationaltoday.com/national-garlic-day/" },
  "04-20": { "name": "National Banana Foster Day", "wikipedia": "Bananas_Foster", "link": "https://nationaltoday.com/national-banana-foster-day/" },
  "04-21": { "name": "National Chocolate Covered Cashews Day", "wikipedia": "Cashew", "link": "https://nationaltoday.com/national-chocolate-covered-cashews-day/" },
  "04-22": { "name": "National Jelly Bean Day", "wikipedia": "Jelly_bean", "link": "https://nationaltoday.com/national-jelly-bean-day/" },
  "04-23": { "name": "National Talk Like Shakespeare Day", "wikipedia": "William_Shakespeare", "link": "https://nationaltoday.com/national-talk-like-shakespeare-day/" },
  "04-24": { "name": "National Pigs in a Blanket Day", "wikipedia": "Pigs_in_a_blanket", "link": "https://nationaltoday.com/national-pigs-in-a-blanket-day/" },
  "04-25": { "name": "National Zucchini Bread Day", "wikipedia": "Zucchini", "link": "https://nationaltoday.com/national-zucchini-bread-day/" },
  "04-26": { "name": "National Pretzel Day", "wikipedia": "Pretzel", "link": "https://nationaltoday.com/national-pretzel-day/" },
  "04-27": { "name": "National Prime Rib Day", "wikipedia": "Standing_rib_roast", "link": "https://nationaltoday.com/national-prime-rib-day/" },
  "04-28": { "name": "National Blueberry Pie Day", "wikipedia": "Blueberry_pie", "link": "https://nationaltoday.com/national-blueberry-pie-day/" },
  "04-29": { "name": "National Shrimp Scampi Day", "wikipedia": "Shrimp_and_prawn_as_food", "link": "https://nationaltoday.com/national-shrimp-scampi-day/" },
  "04-30": { "name": "National Bubble Tea Day", "wikipedia": "Bubble_tea", "link": "https://nationaltoday.com/national-bubble-tea-day/" },

  "05-01": { "name": "National Mother Goose Day", "wikipedia": "Mother_Goose", "link": "https://nationaltoday.com/national-mother-goose-day/" },
  "05-02": { "name": "National Truffle Day", "wikipedia": "Truffle_(confection)", "link": "https://nationaltoday.com/national-truffle-day/" },
  "05-03": { "name": "National Raspberry Tart Day", "wikipedia": "Raspberry", "link": "https://nationaltoday.com/national-raspberry-tart-day/" },
  "05-04": { "name": "Star Wars Day", "wikipedia": "Star_Wars", "link": "https://nationaltoday.com/star-wars-day/" },
  "05-05": { "name": "National Cinco de Mayo", "wikipedia": "Cinco_de_Mayo", "link": "https://nationaltoday.com/cinco-de-mayo/" },
  "05-06": { "name": "National Beverage Day", "wikipedia": "Drink", "link": "https://nationaltoday.com/national-beverage-day/" },
  "05-07": { "name": "National Roast Leg of Lamb Day", "wikipedia": "Lamb_and_mutton", "link": "https://nationaltoday.com/national-roast-leg-of-lamb-day/" },
  "05-08": { "name": "National Coconut Cream Pie Day", "wikipedia": "Coconut_cream_pie", "link": "https://nationaltoday.com/national-coconut-cream-pie-day/" },
  "05-09": { "name": "National Butterscotch Brownie Day", "wikipedia": "Butterscotch", "link": "https://nationaltoday.com/national-butterscotch-brownie-day/" },
  "05-10": { "name": "National Shrimp Day", "wikipedia": "Shrimp_and_prawn_as_food", "link": "https://nationaltoday.com/national-shrimp-day/" },
  "05-11": { "name": "National Eat What You Want Day", "wikipedia": "Food", "link": "https://nationaltoday.com/national-eat-what-you-want-day/" },
  "05-12": { "name": "National Nutty Fudge Day", "wikipedia": "Fudge", "link": "https://nationaltoday.com/national-nutty-fudge-day/" },
  "05-13": { "name": "National Apple Pie Day", "wikipedia": "Apple_pie", "link": "https://nationaltoday.com/national-apple-pie-day/" },
  "05-14": { "name": "National Buttermilk Biscuit Day", "wikipedia": "Biscuit", "link": "https://nationaltoday.com/national-buttermilk-biscuit-day/" },
  "05-15": { "name": "National Chocolate Chip Cookie Day", "wikipedia": "Chocolate_chip_cookie", "link": "https://nationaltoday.com/national-chocolate-chip-cookie-day/" },
  "05-16": { "name": "National Love a Tree Day", "wikipedia": "Tree", "link": "https://nationaltoday.com/national-love-a-tree-day/" },
  "05-17": { "name": "National Cherry Cobbler Day", "wikipedia": "Cobbler_(food)", "link": "https://nationaltoday.com/national-cherry-cobbler-day/" },
  "05-18": { "name": "National Cheese Souffle Day", "wikipedia": "Soufflé", "link": "https://nationaltoday.com/national-cheese-souffle-day/" },
  "05-19": { "name": "National Devil's Food Cake Day", "wikipedia": "Devil%27s_food_cake", "link": "https://nationaltoday.com/national-devils-food-cake-day/" },
  "05-20": { "name": "National Quiche Lorraine Day", "wikipedia": "Quiche", "link": "https://nationaltoday.com/national-quiche-lorraine-day/" },
  "05-21": { "name": "National Strawberries and Cream Day", "wikipedia": "Strawberry", "link": "https://nationaltoday.com/national-strawberries-and-cream-day/" },
  "05-22": { "name": "National Vanilla Pudding Day", "wikipedia": "Vanilla_pudding", "link": "https://nationaltoday.com/national-vanilla-pudding-day/" },
  "05-23": { "name": "National Taffy Day", "wikipedia": "Taffy_(candy)", "link": "https://nationaltoday.com/national-taffy-day/" },
  "05-24": { "name": "National Escargot Day", "wikipedia": "Escargot", "link": "https://nationaltoday.com/national-escargot-day/" },
  "05-25": { "name": "National Wine Day", "wikipedia": "Wine", "link": "https://nationaltoday.com/national-wine-day/" },
  "05-26": { "name": "National Blueberry Cheesecake Day", "wikipedia": "Cheesecake", "link": "https://nationaltoday.com/national-blueberry-cheesecake-day/" },
  "05-27": { "name": "National Grape Popsicle Day", "wikipedia": "Ice_pop", "link": "https://nationaltoday.com/national-grape-popsicle-day/" },
  "05-28": { "name": "National Hamburger Day", "wikipedia": "Hamburger", "link": "https://nationaltoday.com/national-hamburger-day/" },
  "05-29": { "name": "National Coq au Vin Day", "wikipedia": "Coq_au_vin", "link": "https://nationaltoday.com/national-coq-au-vin-day/" },
  "05-30": { "name": "National Mint Julep Day", "wikipedia": "Mint_julep", "link": "https://nationaltoday.com/national-mint-julep-day/" },
  "05-31": { "name": "National Macaroon Day", "wikipedia": "Macaroon", "link": "https://nationaltoday.com/national-macaroon-day/" },

  "06-01": { "name": "National Hazelnut Cake Day", "wikipedia": "Hazelnut", "link": "https://nationaltoday.com/national-hazelnut-cake-day/" },
  "06-02": { "name": "National Rocky Road Day", "wikipedia": "Rocky_road_(ice_cream)", "link": "https://nationaltoday.com/national-rocky-road-day/" },
  "06-03": { "name": "National Egg Day", "wikipedia": "Egg_as_food", "link": "https://nationaltoday.com/national-egg-day/" },
  "06-04": { "name": "National Cheese Day", "wikipedia": "Cheese", "link": "https://nationaltoday.com/national-cheese-day/" },
  "06-05": { "name": "National Gingerbread Day", "wikipedia": "Gingerbread", "link": "https://nationaltoday.com/national-gingerbread-day/" },
  "06-06": { "name": "National Applesauce Cake Day", "wikipedia": "Applesauce", "link": "https://nationaltoday.com/national-applesauce-cake-day/" },
  "06-07": { "name": "National Chocolate Ice Cream Day", "wikipedia": "Chocolate_ice_cream", "link": "https://nationaltoday.com/national-chocolate-ice-cream-day/" },
  "06-08": { "name": "National Jelly-Filled Doughnut Day", "wikipedia": "Doughnut", "link": "https://nationaltoday.com/national-jelly-filled-doughnut-day/" },
  "06-09": { "name": "National Strawberry Rhubarb Pie Day", "wikipedia": "Rhubarb_pie", "link": "https://nationaltoday.com/national-strawberry-rhubarb-pie-day/" },
  "06-10": { "name": "National Iced Tea Day", "wikipedia": "Iced_tea", "link": "https://nationaltoday.com/national-iced-tea-day/" },
  "06-11": { "name": "National Corn on the Cob Day", "wikipedia": "Corn_on_the_cob", "link": "https://nationaltoday.com/national-corn-on-the-cob-day/" },
  "06-12": { "name": "National Peanut Butter Cookie Day", "wikipedia": "Peanut_butter_cookie", "link": "https://nationaltoday.com/national-peanut-butter-cookie-day/" },
  "06-13": { "name": "National Weed Your Garden Day", "wikipedia": "Weed", "link": "https://nationaltoday.com/national-weed-your-garden-day/" },
  "06-14": { "name": "National Strawberry Shortcake Day", "wikipedia": "Strawberry_shortcake", "link": "https://nationaltoday.com/national-strawberry-shortcake-day/" },
  "06-15": { "name": "National Lobster Day", "wikipedia": "Lobster", "link": "https://nationaltoday.com/national-lobster-day/" },
  "06-16": { "name": "National Fudge Day", "wikipedia": "Fudge", "link": "https://nationaltoday.com/national-fudge-day/" },
  "06-17": { "name": "National Apple Strudel Day", "wikipedia": "Strudel", "link": "https://nationaltoday.com/national-apple-strudel-day/" },
  "06-18": { "name": "National Splurge Day", "wikipedia": "Retail_therapy", "link": "https://nationaltoday.com/national-splurge-day/" },
  "06-19": { "name": "National Martini Day", "wikipedia": "Martini_(cocktail)", "link": "https://nationaltoday.com/national-martini-day/" },
  "06-20": { "name": "National Vanilla Milkshake Day", "wikipedia": "Milkshake", "link": "https://nationaltoday.com/national-vanilla-milkshake-day/" },
  "06-21": { "name": "National Peaches and Cream Day", "wikipedia": "Peach", "link": "https://nationaltoday.com/national-peaches-and-cream-day/" },
  "06-22": { "name": "National Onion Ring Day", "wikipedia": "Onion_ring", "link": "https://nationaltoday.com/national-onion-ring-day/" },
  "06-23": { "name": "National Pecan Sandy Day", "wikipedia": "Pecan", "link": "https://nationaltoday.com/national-pecan-sandy-day/" },
  "06-24": { "name": "National Pralines Day", "wikipedia": "Praline", "link": "https://nationaltoday.com/national-pralines-day/" },
  "06-25": { "name": "National Strawberry Parfait Day", "wikipedia": "Parfait", "link": "https://nationaltoday.com/national-strawberry-parfait-day/" },
  "06-26": { "name": "National Chocolate Pudding Day", "wikipedia": "Chocolate_pudding", "link": "https://nationaltoday.com/national-chocolate-pudding-day/" },
  "06-27": { "name": "National Pineapple Day", "wikipedia": "Pineapple", "link": "https://nationaltoday.com/national-pineapple-day/" },
  "06-28": { "name": "National Tapioca Day", "wikipedia": "Tapioca", "link": "https://nationaltoday.com/national-tapioca-day/" },
  "06-29": { "name": "National Waffle Iron Day", "wikipedia": "Waffle_iron", "link": "https://nationaltoday.com/national-waffle-iron-day/" },
  "06-30": { "name": "National Meteor Watch Day", "wikipedia": "Meteoroid", "link": "https://nationaltoday.com/national-meteor-watch-day/" },

  "07-01": { "name": "National Gingersnap Day", "wikipedia": "Ginger_snap", "link": "https://nationaltoday.com/national-gingersnap-day/" },
  "07-02": { "name": "National Anisette Day", "wikipedia": "Anisette", "link": "https://nationaltoday.com/national-anisette-day/" },
  "07-03": { "name": "National Eat Beans Day", "wikipedia": "Bean", "link": "https://nationaltoday.com/national-eat-beans-day/" },
  "07-04": { "name": "National Hot Dog Day", "wikipedia": "Hot_dog", "link": "https://nationaltoday.com/national-hot-dog-day/" },
  "07-05": { "name": "National Apple Turnover Day", "wikipedia": "Turnover_(food)", "link": "https://nationaltoday.com/national-apple-turnover-day/" },
  "07-06": { "name": "National Fried Chicken Day", "wikipedia": "Fried_chicken", "link": "https://nationaltoday.com/national-fried-chicken-day/" },
  "07-07": { "name": "National Strawberry Sundae Day", "wikipedia": "Sundae", "link": "https://nationaltoday.com/national-strawberry-sundae-day/" },
  "07-08": { "name": "National Freezer Pop Day", "wikipedia": "Ice_pop", "link": "https://nationaltoday.com/national-freezer-pop-day/" },
  "07-09": { "name": "National Sugar Cookie Day", "wikipedia": "Sugar_cookie", "link": "https://nationaltoday.com/national-sugar-cookie-day/" },
  "07-10": { "name": "National Piña Colada Day", "wikipedia": "Piña_colada", "link": "https://nationaltoday.com/national-pina-colada-day/" },
  "07-11": { "name": "National Mojito Day", "wikipedia": "Mojito", "link": "https://nationaltoday.com/national-mojito-day/" },
  "07-12": { "name": "National Pecan Pie Day", "wikipedia": "Pecan_pie", "link": "https://nationaltoday.com/national-pecan-pie-day/" },
  "07-13": { "name": "National French Fries Day", "wikipedia": "French_fries", "link": "https://nationaltoday.com/national-french-fries-day/" },
  "07-14": { "name": "National Grand Marnier Day", "wikipedia": "Grand_Marnier", "link": "https://nationaltoday.com/national-grand-marnier-day/" },
  "07-15": { "name": "National Gummy Worm Day", "wikipedia": "Gummy_bear", "link": "https://nationaltoday.com/national-gummy-worm-day/" },
  "07-16": { "name": "National Ice Cream Day", "wikipedia": "Ice_cream", "link": "https://nationaltoday.com/national-ice-cream-day/" },
  "07-17": { "name": "World Emoji Day", "wikipedia": "Emoji", "link": "https://nationaltoday.com/world-emoji-day/" },
  "07-18": { "name": "National Sour Candy Day", "wikipedia": "Sour_(taste)", "link": "https://nationaltoday.com/national-sour-candy-day/" },
  "07-19": { "name": "National Daiquiri Day", "wikipedia": "Daiquiri", "link": "https://nationaltoday.com/national-daiquiri-day/" },
  "07-20": { "name": "National Ice Cream Soda Day", "wikipedia": "Ice_cream_float", "link": "https://nationaltoday.com/national-ice-cream-soda-day/" },
  "07-21": { "name": "National Junk Food Day", "wikipedia": "Junk_food", "link": "https://nationaltoday.com/national-junk-food-day/" },
  "07-22": { "name": "National Mango Day", "wikipedia": "Mango", "link": "https://nationaltoday.com/national-mango-day/" },
  "07-23": { "name": "National Vanilla Ice Cream Day", "wikipedia": "Vanilla_ice_cream", "link": "https://nationaltoday.com/national-vanilla-ice-cream-day/" },
  "07-24": { "name": "National Tequila Day", "wikipedia": "Tequila", "link": "https://nationaltoday.com/national-tequila-day/" },
  "07-25": { "name": "National Hot Fudge Sundae Day", "wikipedia": "Sundae", "link": "https://nationaltoday.com/national-hot-fudge-sundae-day/" },
  "07-26": { "name": "National Bagel and Lox Day", "wikipedia": "Lox", "link": "https://nationaltoday.com/national-bagel-and-lox-day/" },
  "07-27": { "name": "National Crème Brûlée Day", "wikipedia": "Crème_brûlée", "link": "https://nationaltoday.com/national-creme-brulee-day/" },
  "07-28": { "name": "National Milk Chocolate Day", "wikipedia": "Milk_chocolate", "link": "https://nationaltoday.com/national-milk-chocolate-day/" },
  "07-29": { "name": "National Lasagna Day", "wikipedia": "Lasagna", "link": "https://nationaltoday.com/national-lasagna-day/" },
  "07-30": { "name": "National Cheesecake Day", "wikipedia": "Cheesecake", "link": "https://nationaltoday.com/national-cheesecake-day/" },
  "07-31": { "name": "National Avocado Day", "wikipedia": "Avocado", "link": "https://nationaltoday.com/national-avocado-day/" },

  "08-01": { "name": "National Raspberry Cream Pie Day", "wikipedia": "Raspberry", "link": "https://nationaltoday.com/national-raspberry-cream-pie-day/" },
  "08-02": { "name": "National Ice Cream Sandwich Day", "wikipedia": "Ice_cream_sandwich", "link": "https://nationaltoday.com/national-ice-cream-sandwich-day/" },
  "08-03": { "name": "National Watermelon Day", "wikipedia": "Watermelon", "link": "https://nationaltoday.com/national-watermelon-day/" },
  "08-04": { "name": "National Root Beer Float Day", "wikipedia": "Root_beer_float", "link": "https://nationaltoday.com/national-root-beer-float-day/" },
  "08-05": { "name": "National Oyster Day", "wikipedia": "Oyster", "link": "https://nationaltoday.com/national-oyster-day/" },
  "08-06": { "name": "National Wiggle Your Toes Day", "wikipedia": "Toe", "link": "https://nationaltoday.com/national-wiggle-your-toes-day/" },
  "08-07": { "name": "National Lighthouse Day", "wikipedia": "Lighthouse", "link": "https://nationaltoday.com/national-lighthouse-day/" },
  "08-08": { "name": "International Cat Day", "wikipedia": "Cat", "link": "https://nationaltoday.com/international-cat-day/" },
  "08-09": { "name": "National Rice Pudding Day", "wikipedia": "Rice_pudding", "link": "https://nationaltoday.com/national-rice-pudding-day/" },
  "08-10": { "name": "National S'mores Day", "wikipedia": "S%27more", "link": "https://nationaltoday.com/national-smores-day/" },
  "08-11": { "name": "National Presidential Joke Day", "wikipedia": "United_States_President", "link": "https://nationaltoday.com/national-presidential-joke-day/" },
  "08-12": { "name": "National Julienne Fries Day", "wikipedia": "French_fries", "link": "https://nationaltoday.com/national-julienne-fries-day/" },
  "08-13": { "name": "National Filet Mignon Day", "wikipedia": "Filet_mignon", "link": "https://nationaltoday.com/national-filet-mignon-day/" },
  "08-14": { "name": "National Creamsicle Day", "wikipedia": "Creamsicle", "link": "https://nationaltoday.com/national-creamsicle-day/" },
  "08-15": { "name": "National Lemon Meringue Pie Day", "wikipedia": "Lemon_meringue_pie", "link": "https://nationaltoday.com/national-lemon-meringue-pie-day/" },
  "08-16": { "name": "National Rum Day", "wikipedia": "Rum", "link": "https://nationaltoday.com/national-rum-day/" },
  "08-17": { "name": "National Thrift Shop Day", "wikipedia": "Thrift_store", "link": "https://nationaltoday.com/national-thrift-shop-day/" },
  "08-18": { "name": "National Ice Cream Pie Day", "wikipedia": "Ice_cream_cake", "link": "https://nationaltoday.com/national-ice-cream-pie-day/" },
  "08-19": { "name": "National Potato Day", "wikipedia": "Potato", "link": "https://nationaltoday.com/national-potato-day/" },
  "08-20": { "name": "National Chocolate Pecan Pie Day", "wikipedia": "Pecan_pie", "link": "https://nationaltoday.com/national-chocolate-pecan-pie-day/" },
  "08-21": { "name": "National Senior Citizens Day", "wikipedia": "Old_age", "link": "https://nationaltoday.com/national-senior-citizens-day/" },
  "08-22": { "name": "National Eat a Peach Day", "wikipedia": "Peach", "link": "https://nationaltoday.com/national-eat-a-peach-day/" },
  "08-23": { "name": "National Sponge Cake Day", "wikipedia": "Sponge_cake", "link": "https://nationaltoday.com/national-sponge-cake-day/" },
  "08-24": { "name": "National Peach Pie Day", "wikipedia": "Peach", "link": "https://nationaltoday.com/national-peach-pie-day/" },
  "08-25": { "name": "National Whiskey Sour Day", "wikipedia": "Whiskey_sour", "link": "https://nationaltoday.com/national-whiskey-sour-day/" },
  "08-26": { "name": "National Dog Day", "wikipedia": "Dog", "link": "https://nationaltoday.com/national-dog-day/" },
  "08-27": { "name": "National Banana Lovers Day", "wikipedia": "Banana", "link": "https://nationaltoday.com/national-banana-lovers-day/" },
  "08-28": { "name": "National Cherry Turnovers Day", "wikipedia": "Cherry", "link": "https://nationaltoday.com/national-cherry-turnovers-day/" },
  "08-29": { "name": "National More Herbs Less Salt Day", "wikipedia": "Herb", "link": "https://nationaltoday.com/national-more-herbs-less-salt-day/" },
  "08-30": { "name": "National Toasted Marshmallow Day", "wikipedia": "Marshmallow", "link": "https://nationaltoday.com/national-toasted-marshmallow-day/" },
  "08-31": { "name": "National Eat Outside Day", "wikipedia": "Picnic", "link": "https://nationaltoday.com/national-eat-outside-day/" },

  "09-01": { "name": "National Gyro Day", "wikipedia": "Gyro_(food)", "link": "https://nationaltoday.com/national-gyro-day/" },
  "09-02": { "name": "National Blueberry Popsicle Day", "wikipedia": "Ice_pop", "link": "https://nationaltoday.com/national-blueberry-popsicle-day/" },
  "09-03": { "name": "National Skyscraper Day", "wikipedia": "Skyscraper", "link": "https://nationaltoday.com/national-skyscraper-day/" },
  "09-04": { "name": "National Macadamia Nut Day", "wikipedia": "Macadamia", "link": "https://nationaltoday.com/national-macadamia-nut-day/" },
  "09-05": { "name": "National Cheese Pizza Day", "wikipedia": "Pizza", "link": "https://nationaltoday.com/national-cheese-pizza-day/" },
  "09-06": { "name": "National Coffee Ice Cream Day", "wikipedia": "Coffee_ice_cream", "link": "https://nationaltoday.com/national-coffee-ice-cream-day/" },
  "09-07": { "name": "National Beer Lover's Day", "wikipedia": "Beer", "link": "https://nationaltoday.com/national-beer-lovers-day/" },
  "09-08": { "name": "National Date Nut Bread Day", "wikipedia": "Date_palm", "link": "https://nationaltoday.com/national-date-nut-bread-day/" },
  "09-09": { "name": "National Teddy Bear Day", "wikipedia": "Teddy_bear", "link": "https://nationaltoday.com/national-teddy-bear-day/" },
  "09-10": { "name": "National TV Dinner Day", "wikipedia": "TV_dinner", "link": "https://nationaltoday.com/national-tv-dinner-day/" },
  "09-11": { "name": "National Hot Cross Bun Day", "wikipedia": "Hot_cross_bun", "link": "https://nationaltoday.com/national-hot-cross-bun-day/" },
  "09-12": { "name": "National Video Game Day", "wikipedia": "Video_game", "link": "https://nationaltoday.com/national-video-game-day/" },
  "09-13": { "name": "International Chocolate Day", "wikipedia": "Chocolate", "link": "https://nationaltoday.com/international-chocolate-day/" },
  "09-14": { "name": "National Cream-Filled Doughnut Day", "wikipedia": "Doughnut", "link": "https://nationaltoday.com/national-cream-filled-doughnut-day/" },
  "09-15": { "name": "National Creme de Menthe Day", "wikipedia": "Crème_de_menthe", "link": "https://nationaltoday.com/national-creme-de-menthe-day/" },
  "09-16": { "name": "National Guacamole Day", "wikipedia": "Guacamole", "link": "https://nationaltoday.com/national-guacamole-day/" },
  "09-17": { "name": "National Apple Dumpling Day", "wikipedia": "Apple_dumpling", "link": "https://nationaltoday.com/national-apple-dumpling-day/" },
  "09-18": { "name": "National Cheeseburger Day", "wikipedia": "Cheeseburger", "link": "https://nationaltoday.com/national-cheeseburger-day/" },
  "09-19": { "name": "National Butterscotch Pudding Day", "wikipedia": "Butterscotch", "link": "https://nationaltoday.com/national-butterscotch-pudding-day/" },
  "09-20": { "name": "National Pepperoni Pizza Day", "wikipedia": "Pepperoni", "link": "https://nationaltoday.com/national-pepperoni-pizza-day/" },
  "09-21": { "name": "National Chai Tea Day", "wikipedia": "Masala_chai", "link": "https://nationaltoday.com/national-chai-tea-day/" },
  "09-22": { "name": "National Ice Cream Cone Day", "wikipedia": "Ice_cream_cone", "link": "https://nationaltoday.com/national-ice-cream-cone-day/" },
  "09-23": { "name": "National White Chocolate Day", "wikipedia": "White_chocolate", "link": "https://nationaltoday.com/national-white-chocolate-day/" },
  "09-24": { "name": "National Cherries Jubilee Day", "wikipedia": "Cherries_jubilee", "link": "https://nationaltoday.com/national-cherries-jubilee-day/" },
  "09-25": { "name": "National Comic Book Day", "wikipedia": "Comic_book", "link": "https://nationaltoday.com/national-comic-book-day/" },
  "09-26": { "name": "National Pancake Day", "wikipedia": "Pancake", "link": "https://nationaltoday.com/national-pancake-day/" },
  "09-27": { "name": "National Chocolate Milk Day", "wikipedia": "Chocolate_milk", "link": "https://nationaltoday.com/national-chocolate-milk-day/" },
  "09-28": { "name": "National Drink Beer Day", "wikipedia": "Beer", "link": "https://nationaltoday.com/national-drink-beer-day/" },
  "09-29": { "name": "National Coffee Day", "wikipedia": "Coffee", "link": "https://nationaltoday.com/national-coffee-day/" },
  "09-30": { "name": "National Mulled Cider Day", "wikipedia": "Cider", "link": "https://nationaltoday.com/national-mulled-cider-day/" },

  "10-01": { "name": "National Homemade Cookie Day", "wikipedia": "Cookie", "link": "https://nationaltoday.com/national-homemade-cookie-day/" },
  "10-02": { "name": "National Fried Scallops Day", "wikipedia": "Scallop", "link": "https://nationaltoday.com/national-fried-scallops-day/" },
  "10-03": { "name": "National Caramel Custard Day", "wikipedia": "Custard_(food)", "link": "https://nationaltoday.com/national-caramel-custard-day/" },
  "10-04": { "name": "National Cinnamon Roll Day", "wikipedia": "Cinnamon_roll", "link": "https://nationaltoday.com/national-cinnamon-roll-day/" },
  "10-05": { "name": "National Apple Betty Day", "wikipedia": "Apple_crisp", "link": "https://nationaltoday.com/national-apple-betty-day/" },
  "10-06": { "name": "National Noodle Day", "wikipedia": "Noodle", "link": "https://nationaltoday.com/national-noodle-day/" },
  "10-07": { "name": "National Frappe Day", "wikipedia": "Frappuccino", "link": "https://nationaltoday.com/national-frappe-day/" },
  "10-08": { "name": "National Fluffernutter Day", "wikipedia": "Fluffernutter", "link": "https://nationaltoday.com/national-fluffernutter-day/" },
  "10-09": { "name": "National Moldy Cheese Day", "wikipedia": "Mold-ripened_cheese", "link": "https://nationaltoday.com/national-moldy-cheese-day/" },
  "10-10": { "name": "National Angel Food Cake Day", "wikipedia": "Angel_food_cake", "link": "https://nationaltoday.com/national-angel-food-cake-day/" },
  "10-11": { "name": "National Sausage Pizza Day", "wikipedia": "Sausage", "link": "https://nationaltoday.com/national-sausage-pizza-day/" },
  "10-12": { "name": "National Gumbo Day", "wikipedia": "Gumbo", "link": "https://nationaltoday.com/national-gumbo-day/" },
  "10-13": { "name": "National Yorkshire Pudding Day", "wikipedia": "Yorkshire_pudding", "link": "https://nationaltoday.com/national-yorkshire-pudding-day/" },
  "10-14": { "name": "National Dessert Day", "wikipedia": "Dessert", "link": "https://nationaltoday.com/national-dessert-day/" },
  "10-15": { "name": "National Cheese Curd Day", "wikipedia": "Cheese_curd", "link": "https://nationaltoday.com/national-cheese-curd-day/" },
  "10-16": { "name": "World Food Day", "wikipedia": "Food", "link": "https://nationaltoday.com/world-food-day/" },
  "10-17": { "name": "National Pasta Day", "wikipedia": "Pasta", "link": "https://nationaltoday.com/national-pasta-day/" },
  "10-18": { "name": "National Chocolate Cupcake Day", "wikipedia": "Cupcake", "link": "https://nationaltoday.com/national-chocolate-cupcake-day/" },
  "10-19": { "name": "National Seafood Bisque Day", "wikipedia": "Bisque_(food)", "link": "https://nationaltoday.com/national-seafood-bisque-day/" },
  "10-20": { "name": "National Brandied Fruit Day", "wikipedia": "Brandy", "link": "https://nationaltoday.com/national-brandied-fruit-day/" },
  "10-21": { "name": "National Pumpkin Cheesecake Day", "wikipedia": "Pumpkin", "link": "https://nationaltoday.com/national-pumpkin-cheesecake-day/" },
  "10-22": { "name": "National Nut Day", "wikipedia": "Nut_(fruit)", "link": "https://nationaltoday.com/national-nut-day/" },
  "10-23": { "name": "National Boston Cream Pie Day", "wikipedia": "Boston_cream_pie", "link": "https://nationaltoday.com/national-boston-cream-pie-day/" },
  "10-24": { "name": "National Bologna Day", "wikipedia": "Bologna_sausage", "link": "https://nationaltoday.com/national-bologna-day/" },
  "10-25": { "name": "World Pasta Day", "wikipedia": "Pasta", "link": "https://nationaltoday.com/world-pasta-day/" },
  "10-26": { "name": "National Pumpkin Day", "wikipedia": "Pumpkin", "link": "https://nationaltoday.com/national-pumpkin-day/" },
  "10-27": { "name": "National American Beer Day", "wikipedia": "Beer_in_the_United_States", "link": "https://nationaltoday.com/national-american-beer-day/" },
  "10-28": { "name": "National Chocolate Day", "wikipedia": "Chocolate", "link": "https://nationaltoday.com/national-chocolate-day/" },
  "10-29": { "name": "National Oatmeal Day", "wikipedia": "Oatmeal", "link": "https://nationaltoday.com/national-oatmeal-day/" },
  "10-30": { "name": "National Candy Corn Day", "wikipedia": "Candy_corn", "link": "https://nationaltoday.com/national-candy-corn-day/" },
  "10-31": { "name": "National Caramel Apple Day", "wikipedia": "Candy_apple", "link": "https://nationaltoday.com/national-caramel-apple-day/" },

  "11-01": { "name": "National Deep Fried Clams Day", "wikipedia": "Clam", "link": "https://nationaltoday.com/national-deep-fried-clams-day/" },
  "11-02": { "name": "National Deviled Egg Day", "wikipedia": "Deviled_egg", "link": "https://nationaltoday.com/national-deviled-egg-day/" },
  "11-03": { "name": "National Sandwich Day", "wikipedia": "Sandwich", "link": "https://nationaltoday.com/national-sandwich-day/" },
  "11-04": { "name": "National Candy Day", "wikipedia": "Candy", "link": "https://nationaltoday.com/national-candy-day/" },
  "11-05": { "name": "National Doughnut Day", "wikipedia": "Doughnut", "link": "https://nationaltoday.com/national-doughnut-day/" },
  "11-06": { "name": "National Nachos Day", "wikipedia": "Nachos", "link": "https://nationaltoday.com/national-nachos-day/" },
  "11-07": { "name": "National Bittersweet Chocolate with Almonds Day", "wikipedia": "Chocolate", "link": "https://nationaltoday.com/national-bittersweet-chocolate-with-almonds-day/" },
  "11-08": { "name": "National Harvey Wallbanger Day", "wikipedia": "Harvey_Wallbanger", "link": "https://nationaltoday.com/national-harvey-wallbanger-day/" },
  "11-09": { "name": "National Scrapple Day", "wikipedia": "Scrapple", "link": "https://nationaltoday.com/national-scrapple-day/" },
  "11-10": { "name": "National Vanilla Cupcake Day", "wikipedia": "Cupcake", "link": "https://nationaltoday.com/national-vanilla-cupcake-day/" },
  "11-11": { "name": "National Sundae Day", "wikipedia": "Sundae", "link": "https://nationaltoday.com/national-sundae-day/" },
  "11-12": { "name": "National Pizza with the Works Day", "wikipedia": "Pizza_toppings", "link": "https://nationaltoday.com/national-pizza-with-the-works-except-anchovies-day/" },
  "11-13": { "name": "National Indian Pudding Day", "wikipedia": "Indian_pudding", "link": "https://nationaltoday.com/national-indian-pudding-day/" },
  "11-14": { "name": "National Pickle Day", "wikipedia": "Pickled_cucumber", "link": "https://nationaltoday.com/national-pickle-day/" },
  "11-15": { "name": "National Raisin Bran Cereal Day", "wikipedia": "Raisin_Bran", "link": "https://nationaltoday.com/national-raisin-bran-cereal-day/" },
  "11-16": { "name": "National Fast Food Day", "wikipedia": "Fast_food", "link": "https://nationaltoday.com/national-fast-food-day/" },
  "11-17": { "name": "National Baklava Day", "wikipedia": "Baklava", "link": "https://nationaltoday.com/national-baklava-day/" },
  "11-18": { "name": "National Vichyssoise Day", "wikipedia": "Vichyssoise", "link": "https://nationaltoday.com/national-vichyssoise-day/" },
  "11-19": { "name": "National Play Monopoly Day", "wikipedia": "Monopoly_(board_game)", "link": "https://nationaltoday.com/national-play-monopoly-day/" },
  "11-20": { "name": "National Peanut Butter Fudge Day", "wikipedia": "Fudge", "link": "https://nationaltoday.com/national-peanut-butter-fudge-day/" },
  "11-21": { "name": "National Stuffing Day", "wikipedia": "Stuffing", "link": "https://nationaltoday.com/national-stuffing-day/" },
  "11-22": { "name": "National Cranberry Relish Day", "wikipedia": "Cranberry_sauce", "link": "https://nationaltoday.com/national-cranberry-relish-day/" },
  "11-23": { "name": "National Espresso Day", "wikipedia": "Espresso", "link": "https://nationaltoday.com/national-espresso-day/" },
  "11-24": { "name": "National Sardines Day", "wikipedia": "Sardine", "link": "https://nationaltoday.com/national-sardines-day/" },
  "11-25": { "name": "National Parfait Day", "wikipedia": "Parfait", "link": "https://nationaltoday.com/national-parfait-day/" },
  "11-26": { "name": "National Cake Day", "wikipedia": "Cake", "link": "https://nationaltoday.com/national-cake-day/" },
  "11-27": { "name": "National Bavarian Cream Pie Day", "wikipedia": "Cream_pie", "link": "https://nationaltoday.com/national-bavarian-cream-pie-day/" },
  "11-28": { "name": "National French Onion Soup Day", "wikipedia": "French_onion_soup", "link": "https://nationaltoday.com/national-french-onion-soup-day/" },
  "11-29": { "name": "National Lemon Cream Pie Day", "wikipedia": "Lemon_meringue_pie", "link": "https://nationaltoday.com/national-lemon-cream-pie-day/" },
  "11-30": { "name": "National Mousse Day", "wikipedia": "Mousse_(food)", "link": "https://nationaltoday.com/national-mousse-day/" },

  "12-01": { "name": "National Fried Pie Day", "wikipedia": "Fried_pie", "link": "https://nationaltoday.com/national-fried-pie-day/" },
  "12-02": { "name": "National Fritters Day", "wikipedia": "Fritter", "link": "https://nationaltoday.com/national-fritters-day/" },
  "12-03": { "name": "National Peppermint Latte Day", "wikipedia": "Peppermint", "link": "https://nationaltoday.com/national-peppermint-latte-day/" },
  "12-04": { "name": "National Cookie Day", "wikipedia": "Cookie", "link": "https://nationaltoday.com/national-cookie-day/" },
  "12-05": { "name": "National Comfort Food Day", "wikipedia": "Comfort_food", "link": "https://nationaltoday.com/national-comfort-food-day/" },
  "12-06": { "name": "National Microwave Oven Day", "wikipedia": "Microwave_oven", "link": "https://nationaltoday.com/national-microwave-oven-day/" },
  "12-07": { "name": "National Cotton Candy Day", "wikipedia": "Cotton_candy", "link": "https://nationaltoday.com/national-cotton-candy-day/" },
  "12-08": { "name": "National Brownie Day", "wikipedia": "Chocolate_brownie", "link": "https://nationaltoday.com/national-brownie-day/" },
  "12-09": { "name": "National Pastry Day", "wikipedia": "Pastry", "link": "https://nationaltoday.com/national-pastry-day/" },
  "12-10": { "name": "National Lager Day", "wikipedia": "Lager", "link": "https://nationaltoday.com/national-lager-day/" },
  "12-11": { "name": "National Noodle Ring Day", "wikipedia": "Noodle", "link": "https://nationaltoday.com/national-noodle-ring-day/" },
  "12-12": { "name": "National Cocoa Day", "wikipedia": "Hot_chocolate", "link": "https://nationaltoday.com/national-cocoa-day/" },
  "12-13": { "name": "National Gingerbread Man Cookie Day", "wikipedia": "Gingerbread_man", "link": "https://nationaltoday.com/national-gingerbread-house-day/" },
  "12-14": { "name": "National Biscuits and Gravy Day", "wikipedia": "Biscuits_and_gravy", "link": "https://nationaltoday.com/national-biscuits-and-gravy-day/" },
  "12-15": { "name": "National Lemon Cupcake Day", "wikipedia": "Cupcake", "link": "https://nationaltoday.com/national-lemon-cupcake-day/" },
  "12-16": { "name": "National Chocolate Covered Anything Day", "wikipedia": "Chocolate_coating", "link": "https://nationaltoday.com/national-chocolate-covered-anything-day/" },
  "12-17": { "name": "National Maple Syrup Day", "wikipedia": "Maple_syrup", "link": "https://nationaltoday.com/national-maple-syrup-day/" },
  "12-18": { "name": "National Roast Suckling Pig Day", "wikipedia": "Suckling_pig", "link": "https://nationaltoday.com/national-roast-suckling-pig-day/" },
  "12-19": { "name": "National Hard Candy Day", "wikipedia": "Hard_candy", "link": "https://nationaltoday.com/national-hard-candy-day/" },
  "12-20": { "name": "National Sangria Day", "wikipedia": "Sangria", "link": "https://nationaltoday.com/national-sangria-day/" },
  "12-21": { "name": "National Crossword Puzzle Day", "wikipedia": "Crossword", "link": "https://nationaltoday.com/national-crossword-puzzle-day/" },
  "12-22": { "name": "National Short Film Day", "wikipedia": "Short_film", "link": "https://nationaltoday.com/national-short-film-day/" },
  "12-23": { "name": "National Pfeffernüsse Day", "wikipedia": "Pfeffernüsse", "link": "https://nationaltoday.com/national-pfeffernusse-day/" },
  "12-24": { "name": "National Eggnog Day", "wikipedia": "Eggnog", "link": "https://nationaltoday.com/national-eggnog-day/" },
  "12-25": { "name": "National Pumpkin Pie Day", "wikipedia": "Pumpkin_pie", "link": "https://nationaltoday.com/national-pumpkin-pie-day/" },
  "12-26": { "name": "National Candy Cane Day", "wikipedia": "Candy_cane", "link": "https://nationaltoday.com/national-candy-cane-day/" },
  "12-27": { "name": "National Fruitcake Day", "wikipedia": "Fruitcake", "link": "https://nationaltoday.com/national-fruitcake-day/" },
  "12-28": { "name": "National Card Playing Day", "wikipedia": "Playing_card", "link": "https://nationaltoday.com/national-card-playing-day/" },
  "12-29": { "name": "National Pepper Pot Soup Day", "wikipedia": "Pepper_pot_soup", "link": "https://nationaltoday.com/national-pepper-pot-soup-day/" },
  "12-30": { "name": "National Bicarbonate of Soda Day", "wikipedia": "Sodium_bicarbonate", "link": "https://nationaltoday.com/national-bicarbonate-of-soda-day/" },
  "12-31": { "name": "National Champagne Day", "wikipedia": "Champagne", "link": "https://nationaltoday.com/national-champagne-day/" }
}
